setup.py
udacity_distributions_alcheng_test/Binomialdistribution.py
udacity_distributions_alcheng_test/Gaussiandistribution.py
udacity_distributions_alcheng_test/Generaldistribution.py
udacity_distributions_alcheng_test/__init__.py
udacity_distributions_alcheng_test.egg-info/PKG-INFO
udacity_distributions_alcheng_test.egg-info/SOURCES.txt
udacity_distributions_alcheng_test.egg-info/dependency_links.txt
udacity_distributions_alcheng_test.egg-info/not-zip-safe
udacity_distributions_alcheng_test.egg-info/top_level.txt